[
    {
    "总注释": "这部分为规则语言说明文档， to be completed!"
    },
  
    {"alias_head":
      [
        [{"TAG": {"IN": ["NR", "NN", "JJ"]}, "LENGTH": {">=": 2}}, {"IS_PUNCT": true, "OP": "?"}, {"IS_SPACE": true, "OP": "?"}, {"TEXT": {"IN": ["又名", "别名", "别称", "又称", "也叫","昵称", "学名", "称为", "又称为", "被称作", "又称作", "被称为","名叫"]}}],
        [{"TAG": {"IN": ["NR", "NN", "JJ"]}}, {"TAG": {"IN": ["_SP"]}}, {"TEXT": {"IN": ["又名", "别名", "别称", "又称", "也叫","昵称", "学名", "称为", "又称为", "被称作", "又称作", "被称为", "名叫"]}}]
      ],
      "注释": "alias 关系提取的 A"
    },
  
    {"alias_tail":
      [
        [{"TEXT": {"IN": ["又名", "别名", "别称", "又称", "也叫","昵称", "学名", "称为", "又称为", "被称作", "又称作", "被称为", "名叫"]}}, {"IS_PUNCT": true, "OP": "?"}, {"IS_SPACE": true, "OP": "?"}, {"TAG": {"IN": ["NR", "NN", "JJ"]}, "LENGTH": {">=": 2}}]
      ],
      "注释": "alias 关系提取的 B"
    },
  
    {"alias_trigger":
      ["又名", "别名", "别称", "又称", "也叫","昵称", "学名", "称为", "又称为", "被称作", "又称作", "被称为", "名叫"],
      "注释": "alias 关系提取的触发词"
    },
  
    {"alias_filter":
      ["ml"],
      "注释": "alias 关系提取时需要过滤掉的语词"
    }
  ]
  